sqlserver/__init__.py
sqlserver-0.0.17.1.dist-info/METADATA
sqlserver-0.0.17.1.dist-info/WHEEL
sqlserver-0.0.17.1.dist-info/top_level.txt
sqlserver-0.0.17.1.dist-info/RECORD
