Metadata-Version: 2.1
Name: sqlserver
Version: 0.0.17.1
Summary: a module that makes queries easier to SQL Server than PYODBC
Home-page: https://www.adgstudios.co.za
Author: Ashlin Darius Govindasamy
Author-email: adg@adgstudios.co.za
License: MIT
Platform: UNKNOWN
Classifier: Programming Language :: Python :: 3
Classifier: License :: OSI Approved :: MIT License
Classifier: Operating System :: OS Independent
